gridai/__about__.py
gridai/__init__.py
gridai/analyze_dataset.py
gridai/constants.py
gridai/create_dataset.py
gridai/exceptions.py
gridai/gdm_mapper.py
gridai/interfaces.py
gridai/plot_dataset.py
gridai/util.py
gridai/cli/__init__.py
gridai/cli/cli.py
gridai-1.1.0.dist-info/METADATA
gridai-1.1.0.dist-info/WHEEL
gridai-1.1.0.dist-info/entry_points.txt
gridai-1.1.0.dist-info/licenses/LICENSE.txt
gridai-1.1.0.dist-info/RECORD
