Metadata-Version: 2.3
Name: gridai
Version: 1.1.0
Summary: Python package for building graph dataset from GDM system.
Project-URL: Documentation, https://github.nrel.gov/GATES-TLDRD/graph-dataset#readme
Project-URL: Issues, https://github.nrel.gov/GATES-TLDRD/graph-dataset/issues
Project-URL: Source, https://github.nrel.gov/GATES-TLDRD/graph-dataset
Author-email: Kapil Duwadi <Kapil.Duwadi@nrel.gov>, Aadil Latif <Aadil.Latif@nrel.gov>, Andrew Glaws <Andrew.Glaws@nrel.gov>
License: BSD-3-Clause
Keywords: distribution system,grid-data-models,python,pytorch_geometric
Classifier: Programming Language :: Python
Classifier: Programming Language :: Python :: 3.11
Requires-Python: >=3.11
Requires-Dist: click~=8.1.7
Requires-Dist: grid-data-models~=1.1.0
Requires-Dist: matplotlib~=3.9.2
Requires-Dist: networkx~=3.4.2
Requires-Dist: polars~=1.12.0
Requires-Dist: torch-geometric~=2.6.1
Requires-Dist: torch~=2.5.0
Provides-Extra: dev
Requires-Dist: pre-commit; extra == 'dev'
Requires-Dist: pytest; extra == 'dev'
Requires-Dist: pytest-cov; extra == 'dev'
Requires-Dist: ruff; extra == 'dev'
Provides-Extra: doc
Requires-Dist: autodoc-pydantic; extra == 'doc'
Requires-Dist: myst-parser; extra == 'doc'
Requires-Dist: pydata-sphinx-theme; extra == 'doc'
Requires-Dist: sphinx; extra == 'doc'
Requires-Dist: sphinxcontrib-mermaid; extra == 'doc'
